ikologikapi/IkologikApi.py
ikologikapi/IkologikApiCredentials.py
ikologikapi/IkologikException.py
ikologikapi/__init__.py
ikologikapi/dataiterator/GraphDataIterator.py
ikologikapi/dataiterator/GraphDataIteratorMeter.py
ikologikapi/dataiterator/__init__.py
ikologikapi/domain/AbstractIkologikCustomerFieldType.py
ikologikapi/domain/AbstractIkologikCustomerObject.py
ikologikapi/domain/AbstractIkologikInstallationFieldType.py
ikologikapi/domain/AbstractIkologikInstallationObject.py
ikologikapi/domain/AbstractIkologikObject.py
ikologikapi/domain/Alert.py
ikologikapi/domain/AlertType.py
ikologikapi/domain/Asset.py
ikologikapi/domain/AssetType.py
ikologikapi/domain/AssetTypeFieldType.py
ikologikapi/domain/Batch.py
ikologikapi/domain/BatchType.py
ikologikapi/domain/Customer.py
ikologikapi/domain/CustomerShopProduct.py
ikologikapi/domain/CustomerShopProductGroup.py
ikologikapi/domain/CustomerShopProductImage.py
ikologikapi/domain/Dashboard.py
ikologikapi/domain/DashboardWidget.py
ikologikapi/domain/DataImport.py
ikologikapi/domain/DataImportType.py
ikologikapi/domain/Domain.py
ikologikapi/domain/Graph.py
ikologikapi/domain/GraphAlert.py
ikologikapi/domain/GraphData.py
ikologikapi/domain/GraphMeter.py
ikologikapi/domain/InstallationShopProduct.py
ikologikapi/domain/InstallationShopProductGroup.py
ikologikapi/domain/InstallationShopProductImage.py
ikologikapi/domain/MaintenanceTask.py
ikologikapi/domain/MaintenanceType.py
ikologikapi/domain/MaintenanceTypeFieldType.py
ikologikapi/domain/Parameter.py
ikologikapi/domain/Report.py
ikologikapi/domain/ReportType.py
ikologikapi/domain/ReportTypeFieldType.py
ikologikapi/domain/Search.py
ikologikapi/domain/Tag.py
ikologikapi/domain/TagAlertType.py
ikologikapi/domain/__init__.py
ikologikapi/services/AbstractIkologikCustomerService.py
ikologikapi/services/AbstractIkologikInstallationService.py
ikologikapi/services/AbstractIkologikService.py
ikologikapi/services/AlertService.py
ikologikapi/services/AlertTypeService.py
ikologikapi-1.1.55.dist-info/LICENSE
ikologikapi-1.1.55.dist-info/METADATA
ikologikapi-1.1.55.dist-info/WHEEL
ikologikapi-1.1.55.dist-info/top_level.txt
ikologikapi-1.1.55.dist-info/RECORD
