Metadata-Version: 2.1
Name: ikologikapi
Version: 1.1.55
Summary: Ikologik API
Home-page: UNKNOWN
Author: Ikologik
Author-email: development@ikologik.com
License: MIT
Platform: UNKNOWN
Requires-Python: >=3.9
License-File: LICENSE
Requires-Dist: requests (==2.26.0)
